aiodebug/__init__.py
aiodebug/hang_inspection.py
aiodebug/log_slow_callbacks.py
aiodebug/logging_compat.py
aiodebug/monitor_loop_lag.py
aiodebug/testing/__init__.py
aiodebug/testing/time_dilated_loop.py
aiodebug-2.3.0.dist-info/LICENSE
aiodebug-2.3.0.dist-info/METADATA
aiodebug-2.3.0.dist-info/WHEEL
aiodebug-2.3.0.dist-info/top_level.txt
aiodebug-2.3.0.dist-info/RECORD
