Metadata-Version: 2.1
Name: aiodebug
Version: 2.3.0
Summary: A tiny library for monitoring and testing asyncio programs
Home-page: https://gitlab.com/quantlane/libs/aiodebug
Author: Quantlane
Author-email: code@quantlane.com
License: Apache 2.0
Platform: UNKNOWN
Classifier: License :: OSI Approved :: Apache Software License
Classifier: Natural Language :: English
Classifier: Programming Language :: Python :: 3 :: Only
Classifier: Programming Language :: Python :: 3.8
Classifier: Programming Language :: Python :: 3.9
Classifier: Programming Language :: Python :: 3.10
Requires-Dist: typing-extensions (<5.0.0,>=3.7.0)
Provides-Extra: logwood
Requires-Dist: logwood (<4.0.0,>=3.0.0) ; extra == 'logwood'
